{
  "cost": 0.020000000000000018,
  "keywords_analyzed": 10,
  "gaps_found": 10,
  "results": [
    {
      "keyword": "tarifa plana autonomos 2026",
      "total_results": 0,
      "competitor_positions": {},
      "is_gap": true,
      "top_3_domains": []
    },
    {
      "keyword": "gastos deducibles autonomos 2026",
      "total_results": 0,
      "competitor_positions": {},
      "is_gap": true,
      "top_3_domains": []
    },
    {
      "keyword": "modelo 130 autonomos 2026",
      "total_results": 0,
      "competitor_positions": {},
      "is_gap": true,
      "top_3_domains": []
    },
    {
      "keyword": "declarar renta autonomos 2026",
      "total_results": 0,
      "competitor_positions": {},
      "is_gap": true,
      "top_3_domains": []
    },
    {
      "keyword": "cuota autonomos 2026",
      "total_results": 0,
      "competitor_positions": {},
      "is_gap": true,
      "top_3_domains": []
    },
    {
      "keyword": "iva deducible autonomos",
      "total_results": 0,
      "competitor_positions": {},
      "is_gap": true,
      "top_3_domains": []
    },
    {
      "keyword": "retenciones irpf autonomos",
      "total_results": 0,
      "competitor_positions": {},
      "is_gap": true,
      "top_3_domains": []
    },
    {
      "keyword": "factura electronica autonomos",
      "total_results": 0,
      "competitor_positions": {},
      "is_gap": true,
      "top_3_domains": []
    },
    {
      "keyword": "darse de alta autonomo",
      "total_results": 0,
      "competitor_positions": {},
      "is_gap": true,
      "top_3_domains": []
    },
    {
      "keyword": "calendario fiscal autonomos 2026",
      "total_results": 0,
      "competitor_positions": {},
      "is_gap": true,
      "top_3_domains": []
    }
  ]
}