{
  "cost": 0.075,
  "total_keywords": 190,
  "results": [
    {
      "keyword": "taxdown",
      "volume": 60500,
      "cpc": 0.11,
      "competition_index": 24
    },
    {
      "keyword": "gestorias online",
      "volume": 2900,
      "cpc": 8.39,
      "competition_index": 61
    },
    {
      "keyword": "taxdown opiniones",
      "volume": 2400,
      "cpc": 4.74,
      "competition_index": 11
    },
    {
      "keyword": "infoautonomos",
      "volume": 1600,
      "cpc": 8.57,
      "competition_index": 14
    },
    {
      "keyword": "onlytax",
      "volume": 880,
      "cpc": 0.77,
      "competition_index": 30
    },
    {
      "keyword": "taxdown renta",
      "volume": 720,
      "cpc": 0.89,
      "competition_index": 42
    },
    {
      "keyword": "fiscaliza",
      "volume": 590,
      "cpc": 0,
      "competition_index": 3
    },
    {
      "keyword": "gestoría online autónomos",
      "volume": 590,
      "cpc": 12.68,
      "competition_index": 62
    },
    {
      "keyword": "gestoria online autonomo",
      "volume": 590,
      "cpc": 12.68,
      "competition_index": 62
    },
    {
      "keyword": "gestorias online autonomos",
      "volume": 590,
      "cpc": 12.68,
      "competition_index": 62
    },
    {
      "keyword": "taxdown precio",
      "volume": 590,
      "cpc": 2.98,
      "competition_index": 17
    },
    {
      "keyword": "fiscalizacion",
      "volume": 590,
      "cpc": 0,
      "competition_index": 3
    },
    {
      "keyword": "taxdown simulador",
      "volume": 390,
      "cpc": 2,
      "competition_index": 9
    },
    {
      "keyword": "gestor autonomo online",
      "volume": 320,
      "cpc": 16.92,
      "competition_index": 58
    },
    {
      "keyword": "opiniones taxdown",
      "volume": 320,
      "cpc": 7.02,
      "competition_index": 7
    },
    {
      "keyword": "opiniones de taxdown",
      "volume": 320,
      "cpc": 5.4,
      "competition_index": 5
    },
    {
      "keyword": "planes taxdown",
      "volume": 320,
      "cpc": 1.37,
      "competition_index": 12
    },
    {
      "keyword": "taxdown telefono",
      "volume": 260,
      "cpc": 3.31,
      "competition_index": 18
    },
    {
      "keyword": "taxdown es fiable",
      "volume": 260,
      "cpc": 8.46,
      "competition_index": 8
    },
    {
      "keyword": "descuento taxdown",
      "volume": 260,
      "cpc": 2.6,
      "competition_index": 26
    },
    {
      "keyword": "taxdown es gratis",
      "volume": 260,
      "cpc": 2.61,
      "competition_index": 10
    },
    {
      "keyword": "declarando.es",
      "volume": 210,
      "cpc": 3.47,
      "competition_index": 43
    },
    {
      "keyword": "declarando es",
      "volume": 210,
      "cpc": 3.47,
      "competition_index": 43
    },
    {
      "keyword": "asesoria online autonomos",
      "volume": 210,
      "cpc": 8.91,
      "competition_index": 60
    },
    {
      "keyword": "asesoria autonomo online",
      "volume": 210,
      "cpc": 8.91,
      "competition_index": 60
    },
    {
      "keyword": "gestoria online gratuita",
      "volume": 210,
      "cpc": 3.51,
      "competition_index": 55
    },
    {
      "keyword": "asesoria online autonomo",
      "volume": 210,
      "cpc": 8.91,
      "competition_index": 60
    },
    {
      "keyword": "asesoria online autónomos",
      "volume": 210,
      "cpc": 8.91,
      "competition_index": 60
    },
    {
      "keyword": "taxdown planes",
      "volume": 210,
      "cpc": 0.56,
      "competition_index": 27
    },
    {
      "keyword": "gestoria online para autonomos",
      "volume": 170,
      "cpc": 12.06,
      "competition_index": 63
    },
    {
      "keyword": "gestoría online para autónomos",
      "volume": 170,
      "cpc": 12.06,
      "competition_index": 63
    },
    {
      "keyword": "gestoría online para autonomos",
      "volume": 170,
      "cpc": 12.06,
      "competition_index": 63
    },
    {
      "keyword": "precio taxdown",
      "volume": 170,
      "cpc": 2.71,
      "competition_index": 12
    },
    {
      "keyword": "mejor gestoría online autónomos",
      "volume": 140,
      "cpc": 11.61,
      "competition_index": 64
    },
    {
      "keyword": "taxdown autonomos",
      "volume": 140,
      "cpc": 3.68,
      "competition_index": 53
    },
    {
      "keyword": "app taxdown",
      "volume": 140,
      "cpc": 0.5,
      "competition_index": 33
    },
    {
      "keyword": "infoautónomos",
      "volume": 140,
      "cpc": 6.25,
      "competition_index": 30
    },
    {
      "keyword": "taxdown teléfono gratuito",
      "volume": 140,
      "cpc": 2.72,
      "competition_index": 24
    },
    {
      "keyword": "taxdown declaracion renta",
      "volume": 140,
      "cpc": 1.33,
      "competition_index": 36
    },
    {
      "keyword": "taxdown telefono gratuito",
      "volume": 140,
      "cpc": 2.72,
      "competition_index": 24
    },
    {
      "keyword": "gestoría online barata",
      "volume": 110,
      "cpc": 5.86,
      "competition_index": 60
    },
    {
      "keyword": "gestoria online empresas",
      "volume": 110,
      "cpc": 12.26,
      "competition_index": 63
    },
    {
      "keyword": "gestoría online empresas",
      "volume": 110,
      "cpc": 12.26,
      "competition_index": 63
    },
    {
      "keyword": "gestoria online empresa",
      "volume": 110,
      "cpc": 12.26,
      "competition_index": 63
    },
    {
      "keyword": "taxdown gratis",
      "volume": 110,
      "cpc": 3.76,
      "competition_index": 10
    },
    {
      "keyword": "telefono taxdown",
      "volume": 110,
      "cpc": 3.14,
      "competition_index": 14
    },
    {
      "keyword": "taxdown descuento",
      "volume": 110,
      "cpc": 2.56,
      "competition_index": 28
    },
    {
      "keyword": "es fiable taxdown",
      "volume": 110,
      "cpc": 7.17,
      "competition_index": 9
    },
    {
      "keyword": "gestoria online opiniones",
      "volume": 110,
      "cpc": 4.21,
      "competition_index": 41
    },
    {
      "keyword": "taxdown reseñas",
      "volume": 110,
      "cpc": 2.86,
      "competition_index": 4
    },
    {
      "keyword": "asesoria online empresas",
      "volume": 90,
      "cpc": 10.69,
      "competition_index": 56
    },
    {
      "keyword": "taxdown app",
      "volume": 90,
      "cpc": 0.42,
      "competition_index": 33
    },
    {
      "keyword": "info autonomos",
      "volume": 90,
      "cpc": 10.58,
      "competition_index": 39
    },
    {
      "keyword": "taxdown contacto",
      "volume": 90,
      "cpc": 5.17,
      "competition_index": 19
    },
    {
      "keyword": "renta taxdown",
      "volume": 90,
      "cpc": 1.21,
      "competition_index": 39
    },
    {
      "keyword": "taxdown que es",
      "volume": 90,
      "cpc": 0.88,
      "competition_index": 14
    },
    {
      "keyword": "asesoria online pymes",
      "volume": 70,
      "cpc": 18.79,
      "competition_index": 59
    },
    {
      "keyword": "taxdown es",
      "volume": 70,
      "cpc": 0.5,
      "competition_index": 47
    },
    {
      "keyword": "taxdown criptomonedas",
      "volume": 70,
      "cpc": 7.09,
      "competition_index": 6
    },
    {
      "keyword": "declaracion de la renta taxdown",
      "volume": 70,
      "cpc": 1,
      "competition_index": 33
    },
    {
      "keyword": "tax down precio",
      "volume": 70,
      "cpc": 2.88,
      "competition_index": 17
    },
    {
      "keyword": "taxscouts españa",
      "volume": 50,
      "cpc": 1.16,
      "competition_index": 22
    },
    {
      "keyword": "gestoria online pymes",
      "volume": 50,
      "cpc": 9.58,
      "competition_index": 73
    },
    {
      "keyword": "gestoria para autonomos online",
      "volume": 50,
      "cpc": 17.5,
      "competition_index": 42
    },
    {
      "keyword": "declaracion renta taxdown",
      "volume": 50,
      "cpc": 1.35,
      "competition_index": 38
    },
    {
      "keyword": "tax down sl",
      "volume": 50,
      "cpc": 1.16,
      "competition_index": 24
    },
    {
      "keyword": "taxdown borrador",
      "volume": 50,
      "cpc": 2.39,
      "competition_index": 11
    },
    {
      "keyword": "taxdown declaración de la renta",
      "volume": 50,
      "cpc": 1.15,
      "competition_index": 31
    },
    {
      "keyword": "taxdown es segura",
      "volume": 50,
      "cpc": 0,
      "competition_index": 4
    },
    {
      "keyword": "taxdown logo",
      "volume": 50,
      "cpc": 0,
      "competition_index": 0
    },
    {
      "keyword": "taxdown pro",
      "volume": 50,
      "cpc": 4.29,
      "competition_index": 15
    },
    {
      "keyword": "gestoría online autónomos opiniones",
      "volume": 40,
      "cpc": 4.19,
      "competition_index": 59
    },
    {
      "keyword": "precio tax down",
      "volume": 40,
      "cpc": 3.12,
      "competition_index": 10
    },
    {
      "keyword": "taxdown es de fiar",
      "volume": 40,
      "cpc": 9.92,
      "competition_index": 8
    },
    {
      "keyword": "taxdown full",
      "volume": 40,
      "cpc": 3.16,
      "competition_index": 11
    },
    {
      "keyword": "taxdown tarifas",
      "volume": 40,
      "cpc": 2.37,
      "competition_index": 14
    },
    {
      "keyword": "taxdown trustpilot",
      "volume": 40,
      "cpc": 2.64,
      "competition_index": 6
    },
    {
      "keyword": "asesoría online autonomos",
      "volume": 30,
      "cpc": 20.68,
      "competition_index": 16
    },
    {
      "keyword": "taxdown degiro",
      "volume": 30,
      "cpc": 7.86,
      "competition_index": 23
    },
    {
      "keyword": "tax down renta",
      "volume": 30,
      "cpc": 1.1,
      "competition_index": 43
    },
    {
      "keyword": "aplicacion taxdown",
      "volume": 30,
      "cpc": 0.68,
      "competition_index": 31
    },
    {
      "keyword": "cupon descuento taxdown",
      "volume": 30,
      "cpc": 2.03,
      "competition_index": 16
    },
    {
      "keyword": "declaracion taxdown",
      "volume": 30,
      "cpc": 1.28,
      "competition_index": 34
    },
    {
      "keyword": "opinion taxdown",
      "volume": 30,
      "cpc": 2.74,
      "competition_index": 5
    },
    {
      "keyword": "taxdown caixabank",
      "volume": 30,
      "cpc": 0,
      "competition_index": 8
    },
    {
      "keyword": "taxdown crypto",
      "volume": 30,
      "cpc": 0,
      "competition_index": 1
    },
    {
      "keyword": "telefono de taxdown",
      "volume": 30,
      "cpc": 1.72,
      "competition_index": 19
    },
    {
      "keyword": "asesoria online para autonomos",
      "volume": 20,
      "cpc": 8.12,
      "competition_index": 43
    },
    {
      "keyword": "gestoria empresas online",
      "volume": 20,
      "cpc": 16.18,
      "competition_index": 80
    },
    {
      "keyword": "gestoria online para empresas",
      "volume": 20,
      "cpc": 13.53,
      "competition_index": 70
    },
    {
      "keyword": "gestoría online precios",
      "volume": 20,
      "cpc": 1.42,
      "competition_index": 65
    },
    {
      "keyword": "asesoria gestoria online",
      "volume": 20,
      "cpc": 5.22,
      "competition_index": 59
    },
    {
      "keyword": "descargar taxdown",
      "volume": 20,
      "cpc": 0.54,
      "competition_index": 35
    },
    {
      "keyword": "asesoria online para pymes",
      "volume": 20,
      "cpc": 4.24,
      "competition_index": 86
    },
    {
      "keyword": "app tax down",
      "volume": 20,
      "cpc": 0.46,
      "competition_index": 35
    },
    {
      "keyword": "es seguro taxdown",
      "volume": 20,
      "cpc": 8.87,
      "competition_index": 6
    },
    {
      "keyword": "fiscalizat",
      "volume": 20,
      "cpc": 0,
      "competition_index": 0
    },
    {
      "keyword": "opiniones sobre taxdown",
      "volume": 20,
      "cpc": 7.85,
      "competition_index": 9
    },
    {
      "keyword": "tax down app",
      "volume": 20,
      "cpc": 0.82,
      "competition_index": 39
    },
    {
      "keyword": "tax down opiniones",
      "volume": 20,
      "cpc": 10.45,
      "competition_index": 7
    },
    {
      "keyword": "taxdown como funciona",
      "volume": 20,
      "cpc": 4.06,
      "competition_index": 12
    },
    {
      "keyword": "taxdown empleo",
      "volume": 20,
      "cpc": 0,
      "competition_index": 1
    },
    {
      "keyword": "taxdown es de pago",
      "volume": 20,
      "cpc": 3.61,
      "competition_index": 8
    },
    {
      "keyword": "taxdown interactive brokers",
      "volume": 20,
      "cpc": 0,
      "competition_index": 8
    },
    {
      "keyword": "taxdown pais vasco",
      "volume": 20,
      "cpc": 5.06,
      "competition_index": 4
    },
    {
      "keyword": "taxdown sl",
      "volume": 20,
      "cpc": 0,
      "competition_index": 4
    },
    {
      "keyword": "mejor gestoria online autonomos",
      "volume": 10,
      "cpc": 0,
      "competition_index": 57
    },
    {
      "keyword": "mejor asesoria online autonomos",
      "volume": 10,
      "cpc": 5.09,
      "competition_index": 68
    },
    {
      "keyword": "gestoria contable online",
      "volume": 10,
      "cpc": 0,
      "competition_index": 86
    },
    {
      "keyword": "taxdown com mx",
      "volume": 10,
      "cpc": 0,
      "competition_index": 0
    },
    {
      "keyword": "asesoria de empresas online",
      "volume": 10,
      "cpc": 4.14,
      "competition_index": 29
    },
    {
      "keyword": "www taxdown",
      "volume": 10,
      "cpc": 0.83,
      "competition_index": 32
    },
    {
      "keyword": "gestoria online para pymes",
      "volume": 10,
      "cpc": 13.78,
      "competition_index": 86
    },
    {
      "keyword": "gestoría online para pymes",
      "volume": 10,
      "cpc": 13.78,
      "competition_index": 86
    },
    {
      "keyword": "gestoria online autonomos opiniones",
      "volume": 10,
      "cpc": 0,
      "competition_index": 57
    },
    {
      "keyword": "asesoria online para empresas",
      "volume": 10,
      "cpc": 8.32,
      "competition_index": 57
    },
    {
      "keyword": "taxdown evo",
      "volume": 10,
      "cpc": 0,
      "competition_index": 0
    },
    {
      "keyword": "precio gestoria online",
      "volume": 10,
      "cpc": 8.68,
      "competition_index": 86
    },
    {
      "keyword": "taxdown evo banco",
      "volume": 10,
      "cpc": 0,
      "competition_index": 0
    },
    {
      "keyword": "agencia tributaria taxdown",
      "volume": 10,
      "cpc": 0,
      "competition_index": 0
    },
    {
      "keyword": "aplicacion renta taxdown",
      "volume": 10,
      "cpc": 0.44,
      "competition_index": 32
    },
    {
      "keyword": "app taxdown opiniones",
      "volume": 10,
      "cpc": 5.6,
      "competition_index": 10
    },
    {
      "keyword": "asesoría online para autónomos",
      "volume": 10,
      "cpc": 3.12,
      "competition_index": 86
    },
    {
      "keyword": "asesoría online para empresas",
      "volume": 10,
      "cpc": 3.25,
      "competition_index": 64
    },
    {
      "keyword": "autonomos pymes asesoria online",
      "volume": 10,
      "cpc": 9.06,
      "competition_index": 20
    },
    {
      "keyword": "comentarios taxdown",
      "volume": 10,
      "cpc": 0,
      "competition_index": 4
    },
    {
      "keyword": "darse de baja en taxdown",
      "volume": 10,
      "cpc": 0,
      "competition_index": 17
    },
    {
      "keyword": "declaracion de la renta 2021 taxdown",
      "volume": 10,
      "cpc": 0,
      "competition_index": 0
    },
    {
      "keyword": "evo banco taxdown",
      "volume": 10,
      "cpc": 0,
      "competition_index": 0
    },
    {
      "keyword": "evo taxdown",
      "volume": 10,
      "cpc": 0,
      "competition_index": 0
    },
    {
      "keyword": "fiscalizare",
      "volume": 10,
      "cpc": 0,
      "competition_index": 0
    },
    {
      "keyword": "foro taxdown",
      "volume": 10,
      "cpc": 4.38,
      "competition_index": 19
    },
    {
      "keyword": "infoautonomos 2009 sl",
      "volume": 10,
      "cpc": 0,
      "competition_index": 0
    },
    {
      "keyword": "infoautonomos asesoria",
      "volume": 10,
      "cpc": 0,
      "competition_index": 0
    },
    {
      "keyword": "infoautonomos com",
      "volume": 10,
      "cpc": 10.01,
      "competition_index": 36
    },
    {
      "keyword": "infoautonomos el economista",
      "volume": 10,
      "cpc": 0,
      "competition_index": 0
    },
    {
      "keyword": "infoautonomos sociedad limitada",
      "volume": 10,
      "cpc": 0,
      "competition_index": 0
    },
    {
      "keyword": "infoautonomos telefono",
      "volume": 10,
      "cpc": 0,
      "competition_index": 21
    },
    {
      "keyword": "infoautónomos facturación",
      "volume": 10,
      "cpc": 0,
      "competition_index": 0
    },
    {
      "keyword": "infoautónomos noticias",
      "volume": 10,
      "cpc": 0,
      "competition_index": 0
    },
    {
      "keyword": "opiniones app taxdown",
      "volume": 10,
      "cpc": 0,
      "competition_index": 9
    },
    {
      "keyword": "opiniones tax down",
      "volume": 10,
      "cpc": 0,
      "competition_index": 5
    },
    {
      "keyword": "pedrerol taxdown",
      "volume": 10,
      "cpc": 0,
      "competition_index": 0
    },
    {
      "keyword": "precio de taxdown",
      "volume": 10,
      "cpc": 0,
      "competition_index": 7
    },
    {
      "keyword": "precio renta taxdown",
      "volume": 10,
      "cpc": 3.46,
      "competition_index": 8
    },
    {
      "keyword": "quienes son taxdown",
      "volume": 10,
      "cpc": 0,
      "competition_index": 11
    },
    {
      "keyword": "tax down caixabank",
      "volume": 10,
      "cpc": 0,
      "competition_index": 0
    },
    {
      "keyword": "tax down pedrerol",
      "volume": 10,
      "cpc": 0,
      "competition_index": 0
    },
    {
      "keyword": "tax down tarifas",
      "volume": 10,
      "cpc": 3.42,
      "competition_index": 20
    },
    {
      "keyword": "tax down telefono",
      "volume": 10,
      "cpc": 0,
      "competition_index": 14
    },
    {
      "keyword": "tax scouts españa",
      "volume": 10,
      "cpc": 0,
      "competition_index": 0
    },
    {
      "keyword": "taxdown agencia tributaria",
      "volume": 10,
      "cpc": 4.17,
      "competition_index": 13
    },
    {
      "keyword": "taxdown app opiniones",
      "volume": 10,
      "cpc": 0,
      "competition_index": 14
    },
    {
      "keyword": "taxdown com",
      "volume": 10,
      "cpc": 0,
      "competition_index": 16
    },
    {
      "keyword": "taxdown comentarios",
      "volume": 10,
      "cpc": 3.65,
      "competition_index": 7
    },
    {
      "keyword": "taxdown coste",
      "volume": 10,
      "cpc": 3.09,
      "competition_index": 12
    },
    {
      "keyword": "taxdown declaracion conjunta",
      "volume": 10,
      "cpc": 1.91,
      "competition_index": 4
    },
    {
      "keyword": "taxdown deducciones",
      "volume": 10,
      "cpc": 2.56,
      "competition_index": 8
    },
    {
      "keyword": "taxdown es gratuita",
      "volume": 10,
      "cpc": 3.21,
      "competition_index": 8
    },
    {
      "keyword": "taxdown es gratuito",
      "volume": 10,
      "cpc": 0,
      "competition_index": 7
    },
    {
      "keyword": "taxdown estafa",
      "volume": 10,
      "cpc": 0,
      "competition_index": 3
    },
    {
      "keyword": "taxdown etoro",
      "volume": 10,
      "cpc": 3.56,
      "competition_index": 9
    },
    {
      "keyword": "taxdown fiable",
      "volume": 10,
      "cpc": 0,
      "competition_index": 4
    },
    {
      "keyword": "taxdown foro",
      "volume": 10,
      "cpc": 0,
      "competition_index": 0
    },
    {
      "keyword": "taxdown fotos",
      "volume": 10,
      "cpc": 2.5,
      "competition_index": 5
    },
    {
      "keyword": "taxdown funciona",
      "volume": 10,
      "cpc": 11.46,
      "competition_index": 6
    },
    {
      "keyword": "taxdown hacienda",
      "volume": 10,
      "cpc": 0.68,
      "competition_index": 36
    },
    {
      "keyword": "taxdown la caixa",
      "volume": 10,
      "cpc": 0,
      "competition_index": 4
    },
    {
      "keyword": "taxdown no funciona",
      "volume": 10,
      "cpc": 0,
      "competition_index": 8
    },
    {
      "keyword": "taxdown oferta",
      "volume": 10,
      "cpc": 1.23,
      "competition_index": 23
    },
    {
      "keyword": "taxdown pedrerol",
      "volume": 10,
      "cpc": 0,
      "competition_index": 0
    },
    {
      "keyword": "taxdown preguntas",
      "volume": 10,
      "cpc": 0,
      "competition_index": 0
    },
    {
      "keyword": "taxdown pro precio",
      "volume": 10,
      "cpc": 3.36,
      "competition_index": 14
    },
    {
      "keyword": "taxdown renta opiniones",
      "volume": 10,
      "cpc": 10.2,
      "competition_index": 10
    },
    {
      "keyword": "taxdown seguro",
      "volume": 10,
      "cpc": 8.5,
      "competition_index": 2
    },
    {
      "keyword": "taxdown timo",
      "volume": 10,
      "cpc": 0,
      "competition_index": 2
    },
    {
      "keyword": "telefono infoautonomos",
      "volume": 10,
      "cpc": 0,
      "competition_index": 0
    },
    {
      "keyword": "tu asesoria online",
      "volume": 10,
      "cpc": 0.87,
      "competition_index": 79
    },
    {
      "keyword": "tu gestoria online",
      "volume": 10,
      "cpc": 1.37,
      "competition_index": 59
    },
    {
      "keyword": "www taxdown com mx",
      "volume": 10,
      "cpc": 0,
      "competition_index": 0
    },
    {
      "keyword": "www taxdown es",
      "volume": 10,
      "cpc": 1.45,
      "competition_index": 45
    },
    {
      "keyword": "asesor fiscal autónomos españa",
      "volume": 0,
      "cpc": 0,
      "competition_index": 0
    },
    {
      "keyword": "cuánto cobra asesor fiscal",
      "volume": 0,
      "cpc": 0,
      "competition_index": 0
    },
    {
      "keyword": "mejor asesor fiscal online",
      "volume": 0,
      "cpc": 0,
      "competition_index": 0
    },
    {
      "keyword": "fiscalia autonomos",
      "volume": 0,
      "cpc": 0,
      "competition_index": 0
    },
    {
      "keyword": "declaracion de la renta 2022 taxdown",
      "volume": 0,
      "cpc": 0,
      "competition_index": 0
    },
    {
      "keyword": "tax scouts españa opiniones",
      "volume": 0,
      "cpc": 0,
      "competition_index": 0
    },
    {
      "keyword": "tax scouts opiniones españa",
      "volume": 0,
      "cpc": 0,
      "competition_index": 0
    },
    {
      "keyword": "taxdown bnext",
      "volume": 0,
      "cpc": 0,
      "competition_index": 0
    },
    {
      "keyword": "taxscouts españa c gran vía 4 28013 madrid",
      "volume": 0,
      "cpc": 0,
      "competition_index": 0
    }
  ]
}